keylex/JML.py
keylex/KeYLexer.py
keylex/__init__.py
keylex/jmllex.py
keylex/keylex.py
pygments_jml_key-0.1.2.dist-info/LICENSE
pygments_jml_key-0.1.2.dist-info/METADATA
pygments_jml_key-0.1.2.dist-info/WHEEL
pygments_jml_key-0.1.2.dist-info/entry_points.txt
pygments_jml_key-0.1.2.dist-info/top_level.txt
pygments_jml_key-0.1.2.dist-info/RECORD
